theme/__init__.py
theme/theme.py
theme_label-0.3.0.dist-info/LICENSE
theme_label-0.3.0.dist-info/METADATA
theme_label-0.3.0.dist-info/WHEEL
theme_label-0.3.0.dist-info/top_level.txt
theme_label-0.3.0.dist-info/RECORD
