Metadata-Version: 2.1
Name: theme-label
Version: 0.3.0
Summary: Simple CLI labeling tool for text classification
Author: Ilia Moiseev
Author-email: ilia.moiseev.5@yandex.ru
License: MIT
Classifier: Programming Language :: Python :: 3
Classifier: Operating System :: POSIX :: Linux
Requires-Python: >=3.8
License-File: LICENSE
Requires-Dist: pandas
